Metadata-Version: 1.0
Name: eda4ml
Version: 0.1
Summary: Methods for EDA in the ML process
Home-page: UNKNOWN
Author: Athanasios Dritsas
Author-email: thanasis.dritsas@gmail.com
License: UNKNOWN
Platform: UNKNOWN
